{
  "name": "event_object_noemail",
  "labels": {
    "singular": "EEEEvent",
    "plural": "EEEEvents"
  },
  "requiredProperties": [
    "event_id",
    "event_name",
    "event_date",
    "first_name",
    "last_name",
    "rsvp",
    "guests"
  ],
  "properties": [
    {
      "name": "event_name",
      "label": "Event Name",
      "type": "string",
      "fieldType": "text",
      "isPrimaryDisplayLabel": true
    },
    {
      "name": "event_id",
      "label": "Event ID",
      "type": "string",
      "fieldType": "text"
    },
    {
      "name": "first_name",
      "label": "First Name",
      "type": "string",
      "fieldType": "text"
    },
    {
      "name": "last_name",
      "label": "Last Name",
      "type": "string",
      "fieldType": "text"
    },
    {
      "name": "rsvp",
      "label": "RSVP",
      "type": "enumeration",
      "fieldType": "radio",
      "options": [
          {
              "label": "Yes",
              "value": "yes"
          },
          {
              "label": "No",
              "value": "no"
          }
      ]
    },
    {
      "name": "guests",
      "label": "Guests",
      "type": "number",
      "fieldType": "number"
    },
    {
      "name": "event_date",
      "label": "Event Date",
      "type": "date",
      "fieldType": "date"
    }
  ],
  "associatedObjects": [
      "CONTACT"
  ],
  "primaryDisplayProperty": "event_name"
}